LICENSE
README.md
setup.py
arubabank/__init__.py
arubabank/__main__.py
arubabankapi.egg-info/PKG-INFO
arubabankapi.egg-info/SOURCES.txt
arubabankapi.egg-info/dependency_links.txt
arubabankapi.egg-info/requires.txt
arubabankapi.egg-info/top_level.txt