Metadata-Version: 2.1
Name: arubabankapi
Version: 0.2.1
Summary: Unofficial API client for Aruba Bank Online
Home-page: https://github.com/orson1282/arubabank-api
Author: Orson Oehlers
Author-email: orson@oehlers.net
License: OSI Approved :: GNU General Public License v3 (GPLv3)
Keywords: python,banking,aruba,arubabank
Platform: UNKNOWN
Classifier: Programming Language :: Python :: 3
Classifier: Development Status :: 3 - Alpha
Classifier: License :: OSI Approved :: GNU General Public License v3 (GPLv3)
Classifier: Intended Audience :: Developers
Classifier: Intended Audience :: End Users/Desktop
License-File: LICENSE
